odoo/addons/mrp_production_quant_manual_assign/README.rst
odoo/addons/mrp_production_quant_manual_assign/__init__.py
odoo/addons/mrp_production_quant_manual_assign/__manifest__.py
odoo/addons/mrp_production_quant_manual_assign/i18n/it.po
odoo/addons/mrp_production_quant_manual_assign/i18n/mrp_production_quant_manual_assign.pot
odoo/addons/mrp_production_quant_manual_assign/i18n/pt_BR.po
odoo/addons/mrp_production_quant_manual_assign/readme/CONTRIBUTORS.rst
odoo/addons/mrp_production_quant_manual_assign/readme/DESCRIPTION.rst
odoo/addons/mrp_production_quant_manual_assign/readme/USAGE.rst
odoo/addons/mrp_production_quant_manual_assign/static/description/icon.png
odoo/addons/mrp_production_quant_manual_assign/static/description/index.html
odoo/addons/mrp_production_quant_manual_assign/views/mrp_production_views.xml
odoo12_addon_mrp_production_quant_manual_assign-12.0.1.0.0.99.dev10.dist-info/METADATA
odoo12_addon_mrp_production_quant_manual_assign-12.0.1.0.0.99.dev10.dist-info/WHEEL
odoo12_addon_mrp_production_quant_manual_assign-12.0.1.0.0.99.dev10.dist-info/top_level.txt
odoo12_addon_mrp_production_quant_manual_assign-12.0.1.0.0.99.dev10.dist-info/RECORD
